ntubSystem/__init__.py
ntubSystem/__main__.py
ntubSystem/ntubsys.py
ntubSystem-1.0b5.dist-info/LICENSE
ntubSystem-1.0b5.dist-info/METADATA
ntubSystem-1.0b5.dist-info/WHEEL
ntubSystem-1.0b5.dist-info/top_level.txt
ntubSystem-1.0b5.dist-info/RECORD
